LICENSE
MANIFEST.in
README.md
README.rst
paragoo.py
setup.py
paragoo.egg-info/PKG-INFO
paragoo.egg-info/SOURCES.txt
paragoo.egg-info/dependency_links.txt
paragoo.egg-info/requires.txt
paragoo.egg-info/top_level.txt
paragoo.egg-info/zip-safe