Metadata-Version: 1.0
Name: paragoo
Version: 0.2.0
Summary: Static site generator
Home-page: https://github.com/aquatix/paragoo
Author: Michiel Scholten
Author-email: michiel@diginaut.net
License: Apache
Platform: UNKNOWN
